Workbook

Sheet Inventário
A1: As colunas “Status title” e “Status desc.” são fórmula: preenchem-se ao abrir no Excel ou no Google Sheets, e se atualizam se você editar o texto ao lado.
A2: Grupo | B2: Cluster | C2: URL | D2: Meta title (renderizado) | E2: Nº | F2: Status title | G2: Meta description | H2: Nº | I2: Status desc. | J2: H1 | K2: Palavras | L2: Publicado
A3: Conteúdo — artigo | B3: Calçados | C3: https://towerepis.com.br/conhecimento/biqueira-de-composite-ou-de-aco-qual-escolher/ | D3: Biqueira de composite ou de aço: qual escolher · Tower EPI's | E3: 60 | F3: =IF(E2=0,"sem title",IF(E2>60,"longo",IF(E2<30,"curto","ok"))) | G3: Composite e aço protegem os dedos do mesmo jeito pela norma. A escolha é pela atividade: risco elétrico, detector de metal, frio, peso na jornada e custo. | H3: 154 | I3: =IF(H2=0,"sem description",IF(H2>160,"longa",IF(H2<120,"curta","ok"))) | J3: Biqueira de composite ou de aço: qual escolher? | K3: 1189 | L3: 2026-09-04
A4: Conteúdo — artigo | B4: Calçados | C4: https://towerepis.com.br/conhecimento/bota-de-pvc-quando-e-a-resposta-certa/ | D4: Bota de PVC: quando ela resolve · Tower EPI's | E4: 45 | F4: =IF(E3=0,"sem title",IF(E3>60,"longo",IF(E3<30,"curto","ok"))) | G4: Quando a bota de PVC é a escolha certa, o que ela cobra em troca e como decidir entre ela e o calçado fechado impermeável — com o que conferir antes de comprar. | H4: 160 | I4: =IF(H3=0,"sem description",IF(H3>160,"longa",IF(H3<120,"curta","ok"))) | J4: Bota de PVC: quando ela é a resposta certa | K4: 1166 | L4: 2026-09-11
A5: Conteúdo — artigo | B5: Calçados | C5: https://towerepis.com.br/conhecimento/botina-bota-ou-sapato-de-seguranca/ | D5: Botina, bota ou sapato de segurança · Tower EPI's | E5: 49 | F5: =IF(E4=0,"sem title",IF(E4>60,"longo",IF(E4<30,"curto","ok"))) | G5: O que muda entre sapato, botina e bota de cano alto: barreira de entrada, apoio do tornozelo e conforto. A pergunta que resolve, e o erro do cano mais alto. | H5: 156 | I5: =IF(H4=0,"sem description",IF(H4>160,"longa",IF(H4<120,"curta","ok"))) | J5: Botina, bota ou sapato de segurança: quando cada um | K5: 1083 | L5: 2026-09-20
A6: Conteúdo — artigo | B6: Calçados | C6: https://towerepis.com.br/conhecimento/botina-escorrega-o-que-fazer-antes-de-trocar/ | D6: Botina escorregando: antes de trocar · Tower EPI's | E6: 50 | F6: =IF(E5=0,"sem title",IF(E5>60,"longo",IF(E5<30,"curto","ok"))) | G6: A ordem de investigação quando o calçado passa a escorregar: o que mudou, limpar a sola, o produto do piso, e só então o calçado. Com o que não resolve. | H6: 152 | I6: =IF(H5=0,"sem description",IF(H5>160,"longa",IF(H5<120,"curta","ok"))) | J6: Botina escorrega: o que fazer antes de trocar | K6: 1060 | L6: 2026-09-04
A7: Conteúdo — artigo | B7: Calçados | C7: https://towerepis.com.br/conhecimento/botina-que-machuca-calcado-ou-numeracao/ | D7: Botina que machuca: o que fazer antes de trocar · Tower EPI's | E7: 61 | F7: =IF(E6=0,"sem title",IF(E6>60,"longo",IF(E6<30,"curto","ok"))) | G7: Por que a biqueira não amacia, como saber se o problema é a numeração ou a forma do calçado, e quando insistir só piora. Sem truque caseiro. | H7: 140 | I7: =IF(H6=0,"sem description",IF(H6>160,"longa",IF(H6<120,"curta","ok"))) | J7: Botina que machuca: é o calçado ou é a numeração? | K7: 948 | L7: 2026-09-03
A8: Conteúdo — artigo | B8: Normas | C8: https://towerepis.com.br/conhecimento/ca-vencido-o-epi-pode-continuar-em-uso/ | D8: CA vencido: pode continuar usando? · Tower EPI's | E8: 48 | F8: =IF(E7=0,"sem title",IF(E7>60,"longo",IF(E7<30,"curto","ok"))) | G8: O que o vencimento do CA significa na compra, na prateleira e no par que já está no pé de alguém. Com a consulta oficial e o que fazer em cada situação. | H8: 152 | I8: =IF(H7=0,"sem description",IF(H7>160,"longa",IF(H7<120,"curta","ok"))) | J8: CA vencido: o EPI pode continuar em uso? | K8: 1192 | L8: 2026-09-04
A9: Conteúdo — artigo | B9: Calçados | C9: https://towerepis.com.br/conhecimento/calcado-ocupacional-ou-de-seguranca/ | D9: NBR ISO 20345 e 20347: o que muda no calçado · Tower EPI's | E9: 58 | F9: =IF(E8=0,"sem title",IF(E8>60,"longo",IF(E8<30,"curto","ok"))) | G9: As duas normas do calçado profissional, o que cada uma exige da biqueira, e a pergunta que resolve a dúvida na maioria dos casos. | H9: 129 | I9: =IF(H8=0,"sem description",IF(H8>160,"longa",IF(H8<120,"curta","ok"))) | J9: NBR ISO 20345 e 20347: o que muda no calçado profissional | K9: 872 | L9: 2026-08-30
A10: Conteúdo — artigo | B10: Calçados | C10: https://towerepis.com.br/conhecimento/calcado-para-cozinha-como-escolher/ | D10: Qual o melhor calçado para cozinha? · Tower EPI's | E10: 49 | F10: =IF(E9=0,"sem title",IF(E9>60,"longo",IF(E9<30,"curto","ok"))) | G10: Piso molhado, gordura e horas em pé mudam o critério. O que observar no solado e na cobertura, e quando a biqueira entra — revisado por técnico de segurança. | H10: 157 | I10: =IF(H9=0,"sem description",IF(H9>160,"longa",IF(H9<120,"curta","ok"))) | J10: Qual o melhor calçado para trabalhar em cozinha? | K10: 923 | L10: 2026-08-30
A11: Conteúdo — artigo | B11: Calçados | C11: https://towerepis.com.br/conhecimento/calcado-para-quem-trabalha-em-pe-o-dia-todo/ | D11: Calçado para trabalhar em pé o dia todo · Tower EPI's | E11: 53 | F11: =IF(E10=0,"sem title",IF(E10>60,"longo",IF(E10<30,"curto","ok"))) | G11: O que decide o conforto de quem passa o turno em pé: peso do par, amortecimento e numeração, nessa ordem. E o que ajuda sem ser o calçado. | H11: 138 | I11: =IF(H10=0,"sem description",IF(H10>160,"longa",IF(H10<120,"curta","ok"))) | J11: Calçado para quem trabalha em pé o dia todo | K11: 1066 | L11: 2026-09-12
A12: Conteúdo — artigo | B12: Compra | C12: https://towerepis.com.br/conhecimento/como-escolher-fornecedor-de-epi/ | D12: Como escolher fornecedor de EPI · Tower EPI's | E12: 45 | F12: =IF(E11=0,"sem title",IF(E11>60,"longo",IF(E11<30,"curto","ok"))) | G12: O que exigir de um fornecedor de EPI antes de fechar: CA na proposta, descrição do que foi aprovado, reposição e troca de numeração. Com os sinais de risco. | H12: 156 | I12: =IF(H11=0,"sem description",IF(H11>160,"longa",IF(H11<120,"curta","ok"))) | J12: Como escolher um fornecedor de EPI | K12: 990 | L12: 2026-09-05
A13: Conteúdo — artigo | B13: Calçados | C13: https://towerepis.com.br/conhecimento/como-limpar-e-conservar-calcado-de-seguranca/ | D13: Como limpar calçado de segurança · Tower EPI's | E13: 46 | F13: =IF(E12=0,"sem title",IF(E12>60,"longo",IF(E12<30,"curto","ok"))) | G13: A rotina de limpeza e secagem que faz o calçado de trabalho durar, o que nunca fazer com couro e solado, e por que alternar pares rende mais que qualquer produto. | H13: 162 | I13: =IF(H12=0,"sem description",IF(H12>160,"longa",IF(H12<120,"curta","ok"))) | J13: Como limpar e conservar calçado de segurança | K13: 1121 | L13: 2026-09-11
A14: Conteúdo — artigo | B14: Normas | C14: https://towerepis.com.br/conhecimento/empresa-pode-descontar-epi-do-salario/ | D14: Pode descontar EPI do salário? · Tower EPI's | E14: 44 | F14: =IF(E13=0,"sem title",IF(E13>60,"longo",IF(E13<30,"curto","ok"))) | G14: O que a NR-6 resolve sem margem, o que fica para o direito do trabalho e o que evita a discussão no dia a dia. Sem parecer jurídico, com a fonte oficial. | H14: 153 | I14: =IF(H13=0,"sem description",IF(H13>160,"longa",IF(H13<120,"curta","ok"))) | J14: A empresa pode descontar EPI do salário? | K14: 1157 | L14: 2026-09-04
... A39: Conteúdo — artigo | B39: Proteção | C39: https://towerepis.com.br/conhecimento/tipos-de-luva-qual-material-escolher/ | D39: Tipos de luva de proteção: qual usar · Tower EPI's | E39: 50 | F39: =IF(E38=0,"sem title",IF(E38>60,"longo",IF(E38<30,"curto","ok"))) | G39: Nitrílica, látex, vinílica e neoprene comparadas por resistência, tato e modo de falha — e por que a escolha final depende do produto manuseado e do CA da luva. | H39: 160 | I39: =IF(H38=0,"sem description",IF(H38>160,"longa",IF(H38<120,"curta","ok"))) | J39: Nitrílica, látex, vinílica ou neoprene: qual luva usar | K39: 1117 | L39: 2026-09-09
A40: Conteúdo — hub | C40: https://towerepis.com.br/conhecimento/ | D40: Central de conhecimento sobre EPI · Tower EPI's | E40: 47 | F40: =IF(E39=0,"sem title",IF(E39>60,"longo",IF(E39<30,"curto","ok"))) | G40: Textos sobre calçados profissionais, normas, CA e escolha de EPI. Escritos e revisados por técnico de segurança do trabalho, com fonte oficial citada. | H40: 150 | I40: =IF(H39=0,"sem description",IF(H39>160,"longa",IF(H39<120,"curta","ok"))) | J40: Antes de comprar, entenda | K40: 1732
A41: SEO comercial | C41: https://towerepis.com.br/calcados/ | D41: Calçado de segurança e ocupacional em Fortaleza | E41: 47 | F41: =IF(E40=0,"sem title",IF(E40>60,"longo",IF(E40<30,"curto","ok"))) | G41: Calçado de segurança com biqueira, ocupacional e antiderrapante em Fortaleza. Entenda a diferença com quem é técnico de segurança do trabalho. | H41: 142 | I41: =IF(H40=0,"sem description",IF(H40>160,"longa",IF(H40<120,"curta","ok"))) | J41: Calçados de segurança e ocupacionais | K41: 368
A42: SEO comercial | C42: https://towerepis.com.br/calcados/antiderrapantes/ | D42: Sapato antiderrapante em Fortaleza · Tower EPI's | E42: 48 | F42: =IF(E41=0,"sem title",IF(E41>60,"longo",IF(E41<30,"curto","ok"))) | G42: Antiderrapante não é uma coisa só: o ensaio muda com o piso e o contaminante. Como ler a marcação, escolher para molhado ou oleoso e conferir o desgaste. | H42: 153 | I42: =IF(H41=0,"sem description",IF(H41>160,"longa",IF(H41<120,"curta","ok"))) | J42: Calçados antiderrapantes | K42: 478
A43: SEO comercial | C43: https://towerepis.com.br/calcados/comparativo/ | D43: Ocupacional ou de segurança: qual é o seu caso · Tower EPI's | E43: 60 | F43: =IF(E42=0,"sem title",IF(E42>60,"longo",IF(E42<30,"curto","ok"))) | G43: Queda de objeto, tipo de piso e horas em pé: o que pesa na escolha entre os dois, o que a biqueira faz e o que ela não faz. | H43: 123 | I43: =IF(H42=0,"sem description",IF(H42>160,"longa",IF(H42<120,"curta","ok"))) | J43: Calçado ocupacional ou de segurança: qual é o seu caso? | K43: 894
A44: SEO comercial | C44: https://towerepis.com.br/calcados/ocupacionais/ | D44: Calçados ocupacionais em Fortaleza · Tower EPI's | E44: 48 | F44: =IF(E43=0,"sem title",IF(E43>60,"longo",IF(E43<30,"curto","ok"))) | G44: Sem biqueira, para atividades sem risco de queda de objeto: cozinha, saúde, limpeza e serviços. O que observar no solado, na cobertura e na numeração. | H44: 150 | I44: =IF(H43=0,"sem description",IF(H43>160,"longa",IF(H43<120,"curta","ok"))) | J44: Calçados ocupacionais | K44: 477
A45: SEO comercial | C45: https://towerepis.com.br/calcados/seguranca/ | D45: Calçados de segurança em Fortaleza · Tower EPI's | E45: 48 | F45: =IF(E44=0,"sem title",IF(E44>60,"longo",IF(E44<30,"curto","ok"))) | G45: Biqueira de aço ou composite, solado resistente e a classe certa para o piso. O que observar antes de definir a grade da equipe. | H45: 128 | I45: =IF(H44=0,"sem description",IF(H44>160,"longa",IF(H44<120,"curta","ok"))) | J45: Calçados de segurança | K45: 478
A46: SEO comercial | C46: https://towerepis.com.br/empresas/ | D46: Fornecedor de EPI para empresas em Fortaleza | E46: 44 | F46: =IF(E45=0,"sem title",IF(E45>60,"longo",IF(E45<30,"curto","ok"))) | G46: Fornecimento para equipes em Fortaleza e no Ceará, com o CA de cada item no orçamento. Sem CNPJ para começar a conversa — quem responde é um dos dois sócios. | H46: 157 | I46: =IF(H45=0,"sem description",IF(H45>160,"longa",IF(H45<120,"curta","ok"))) | J46: EPI para a sua equipe, escolhido pela atividade | K46: 566
A47: SEO comercial | C47: https://towerepis.com.br/empresas/alimentacao/ | D47: EPI para restaurantes e cozinhas em Fortaleza | E47: 45 | F47: =IF(E46=0,"sem title",IF(E46>60,"longo",IF(E46<30,"curto","ok"))) | G47: Calçado antiderrapante, luva e proteção para equipes de cozinha. Orçamento com o CA de cada item, grade de numeração e entrega em Fortaleza. | H47: 140 | I47: =IF(H46=0,"sem description",IF(H46>160,"longa",IF(H46<120,"curta","ok"))) | J47: EPI para equipes de cozinha e alimentação | K47: 804
A48: SEO comercial | C48: https://towerepis.com.br/empresas/como-atendemos/ | D48: Como funciona o fornecimento para empresas · Tower EPI's | E48: 56 | F48: =IF(E47=0,"sem title",IF(E47>60,"longo",IF(E47<30,"curto","ok"))) | G48: Você conta o que a equipe faz, a gente confere o que é adequado e o orçamento sai com o CA de cada item. Prazo combinado antes de fechar, reposição simples. | H48: 156 | I48: =IF(H47=0,"sem description",IF(H47>160,"longa",IF(H47<120,"curta","ok"))) | J48: Como a gente atende | K48: 526
A49: SEO comercial | C49: https://towerepis.com.br/empresas/construcao/ | D49: Fornecedor de EPI para obras em Fortaleza | E49: 41 | F49: =IF(E48=0,"sem title",IF(E48>60,"longo",IF(E48<30,"curto","ok"))) | G49: Calçado com biqueira, capacete, luva e proteção respiratória para obra. Orçamento com o CA de cada item, entrega em Fortaleza e reposição sem recomeçar. | H49: 152 | I49: =IF(H48=0,"sem description",IF(H48>160,"longa",IF(H48<120,"curta","ok"))) | J49: EPI para equipes de obra | K49: 751
A50: SEO comercial | C50: https://towerepis.com.br/empresas/facilities-e-limpeza/ | D50: EPI para empresas de limpeza em Fortaleza | E50: 41 | F50: =IF(E49=0,"sem title",IF(E49>60,"longo",IF(E49<30,"curto","ok"))) | G50: Luva adequada ao produto, calçado antiderrapante e proteção para os olhos. Orçamento com o CA de cada item e entrega para empresas de limpeza em Fortaleza. | H50: 155 | I50: =IF(H49=0,"sem description",IF(H49>160,"longa",IF(H49<120,"curta","ok"))) | J50: EPI para equipes de limpeza e conservação | K50: 732
A51: SEO comercial | C51: https://towerepis.com.br/empresas/industria/ | D51: Fornecedor de EPI para indústria em Fortaleza | E51: 45 | F51: =IF(E50=0,"sem title",IF(E50>60,"longo",IF(E50<30,"curto","ok"))) | G51: Proteção auditiva, respiratória, calçado e luva definidos por posto de trabalho. Orçamento com o CA de cada item, entrega no Ceará e reposição sem recomeçar. | H51: 157 | I51: =IF(H50=0,"sem description",IF(H50>160,"longa",IF(H50<120,"curta","ok"))) | J51: EPI para indústria, por posto de trabalho | K51: 768
... A89: Institucional / legal | C89: https://towerepis.com.br/termos-de-uso/ | D89: Termos de uso · Tower EPI's | E89: 27 | F89: =IF(E88=0,"sem title",IF(E88>60,"longo",IF(E88<30,"curto","ok"))) | G89: As regras de uso do site da Tower EPI’s: finalidade informativa do conteúdo, orçamento sem compromisso, propriedade do material e limites de responsabilidade. | H89: 158 | I89: =IF(H88=0,"sem description",IF(H88>160,"longa",IF(H88<120,"curta","ok"))) | J89: Termos de uso | K89: 781

Sheet Resumo
A1: Tower EPI's — inventário de title e description
A2: Medido no build de 22/09/2026, em navegador real. Os valores da aba Inventário são os RENDERIZADOS, com o sufixo do site já somado.
A4: Grupo | B4: Páginas | C4: Title ok | D4: Title longo | E4: Desc. ok | F4: Desc. fora
A5: Conteúdo — artigo | B5: =COUNTIF(Inventário!$A$2:$A$88,$A5) | C5: =COUNTIFS(Inventário!$A$2:$A$88,$A5,Inventário!$F$2:$F$88,"ok") | D5: =COUNTIFS(Inventário!$A$2:$A$88,$A5,Inventário!$F$2:$F$88,"longo") | E5: =COUNTIFS(Inventário!$A$2:$A$88,$A5,Inventário!$I$2:$I$88,"ok") | F5: =COUNTIF(Inventário!$A$2:$A$88,$A5)-E5
A6: Conteúdo — hub | B6: =COUNTIF(Inventário!$A$2:$A$88,$A6) | C6: =COUNTIFS(Inventário!$A$2:$A$88,$A6,Inventário!$F$2:$F$88,"ok") | D6: =COUNTIFS(Inventário!$A$2:$A$88,$A6,Inventário!$F$2:$F$88,"longo") | E6: =COUNTIFS(Inventário!$A$2:$A$88,$A6,Inventário!$I$2:$I$88,"ok") | F6: =COUNTIF(Inventário!$A$2:$A$88,$A6)-E6
A7: SEO comercial | B7: =COUNTIF(Inventário!$A$2:$A$88,$A7) | C7: =COUNTIFS(Inventário!$A$2:$A$88,$A7,Inventário!$F$2:$F$88,"ok") | D7: =COUNTIFS(Inventário!$A$2:$A$88,$A7,Inventário!$F$2:$F$88,"longo") | E7: =COUNTIFS(Inventário!$A$2:$A$88,$A7,Inventário!$I$2:$I$88,"ok") | F7: =COUNTIF(Inventário!$A$2:$A$88,$A7)-E7
A8: SEO local | B8: =COUNTIF(Inventário!$A$2:$A$88,$A8) | C8: =COUNTIFS(Inventário!$A$2:$A$88,$A8,Inventário!$F$2:$F$88,"ok") | D8: =COUNTIFS(Inventário!$A$2:$A$88,$A8,Inventário!$F$2:$F$88,"longo") | E8: =COUNTIFS(Inventário!$A$2:$A$88,$A8,Inventário!$I$2:$I$88,"ok") | F8: =COUNTIF(Inventário!$A$2:$A$88,$A8)-E8
A9: Conversão | B9: =COUNTIF(Inventário!$A$2:$A$88,$A9) | C9: =COUNTIFS(Inventário!$A$2:$A$88,$A9,Inventário!$F$2:$F$88,"ok") | D9: =COUNTIFS(Inventário!$A$2:$A$88,$A9,Inventário!$F$2:$F$88,"longo") | E9: =COUNTIFS(Inventário!$A$2:$A$88,$A9,Inventário!$I$2:$I$88,"ok") | F9: =COUNTIF(Inventário!$A$2:$A$88,$A9)-E9
A10: Institucional | B10: =COUNTIF(Inventário!$A$2:$A$88,$A10) | C10: =COUNTIFS(Inventário!$A$2:$A$88,$A10,Inventário!$F$2:$F$88,"ok") | D10: =COUNTIFS(Inventário!$A$2:$A$88,$A10,Inventário!$F$2:$F$88,"longo") | E10: =COUNTIFS(Inventário!$A$2:$A$88,$A10,Inventário!$I$2:$I$88,"ok") | F10: =COUNTIF(Inventário!$A$2:$A$88,$A10)-E10
A11: Institucional / legal | B11: =COUNTIF(Inventário!$A$2:$A$88,$A11) | C11: =COUNTIFS(Inventário!$A$2:$A$88,$A11,Inventário!$F$2:$F$88,"ok") | D11: =COUNTIFS(Inventário!$A$2:$A$88,$A11,Inventário!$F$2:$F$88,"longo") | E11: =COUNTIFS(Inventário!$A$2:$A$88,$A11,Inventário!$I$2:$I$88,"ok") | F11: =COUNTIF(Inventário!$A$2:$A$88,$A11)-E11
A12: TOTAL | B12: =SUM(B5:B11) | C12: =SUM(C5:C11) | D12: =SUM(D5:D11) | E12: =SUM(E5:E11) | F12: =SUM(F5:F11)
A14: Como ler
A15: Title renderizado | B15: O site usa o template "%s · Tower EPI's". O sufixo soma 14 caracteres, e a coluna Nº já os conta — é o que o buscador corta.
A16: Faixa de title | B16: Até 60 caracteres. Acima disso o resultado de busca costuma truncar.
A17: Faixa de description | B17: Entre 120 e 160 caracteres. Fora dessa faixa não é erro, é sinal de revisão.
A18: Congelamento | B18: Title, description e H1 estão congelados até 1º de novembro de 2026, por decisão registrada em docs/10-regra-de-avaliacao.md. Esta planilha é para medir, não para reescrever agora.
A19: Duas exceções conhecidas | B19: Dois títulos publicados antes da guarda de build estouram por 1 e 2 caracteres e são tolerados até a mesma data.
A20: Fonte | B20: Rastreamento em navegador real do build de produção. Nada aqui foi digitado à mão.
A21: Fórmulas | B21: O resumo acima é contagem por fórmula e aparece ao abrir o arquivo no Excel ou no Google Sheets. Os números foram conferidos por fora, um a um, antes da entrega.
